LICENSE
README.md
setup.py
mcfit/__init__.py
mcfit/cosmology.py
mcfit/kernels.py
mcfit/mcfit.py
mcfit/mkfit.py
mcfit/transforms.py
mcfit.egg-info/PKG-INFO
mcfit.egg-info/SOURCES.txt
mcfit.egg-info/dependency_links.txt
mcfit.egg-info/requires.txt
mcfit.egg-info/top_level.txt
mcfit/tests/__init__.py
mcfit/tests/test_mcfit.py
mcfit/tests/test_transforms.py