Metadata-Version: 2.1
Name: mcfit
Version: 0.0.22
Summary: Multiplicatively convolutional fast integral transforms
Home-page: https://github.com/eelregit/mcfit
Author: Yin Li
Author-email: eelregit@gmail.com
License: GPLv3
Keywords: numerical integral transform FFTLog cosmology
License-File: LICENSE
